randomized_tsp/Ant.py
randomized_tsp/AntColony.py
randomized_tsp/Genetic.py
randomized_tsp/SimulatedAnnealing.py
randomized_tsp/__init__.py
randomized_tsp/tsp.py
randomized_tsp/utils.py
randomized_tsp-0.0.2.dist-info/LICENSE
randomized_tsp-0.0.2.dist-info/METADATA
randomized_tsp-0.0.2.dist-info/WHEEL
randomized_tsp-0.0.2.dist-info/top_level.txt
randomized_tsp-0.0.2.dist-info/RECORD
