Metadata-Version: 2.1
Name: randomized-tsp
Version: 0.0.2
Summary: Randomized algorithms for Travelling Salesman Problem
Home-page: https://github.com/akshatkarani/randomized_tsp
Author: Akshat Karani
Author-email: akshatkarani@gmail.com
License: UNKNOWN
Keywords: travelling salesman problem,tsp,randomized algorithm
Platform: UNKNOWN
Classifier: Programming Language :: Python :: 3
Classifier: License :: OSI Approved :: MIT License
Classifier: Operating System :: OS Independent
Requires-Python: >=3.5
